{
    "data": [
        {
            "nombre": "INVENTARIO",
            "descripcion":"",
            "icon": "pi pi-warehouse",
            "childrens": [
                {
                    "nombre": "Inventario",
                    "descripcion": "En la pagina se muestra el inventario disponible",
                    "icon": "pi pi-warehouse",
                    "childrens": [],
                    "tipo": "MENU",
                    "ruta": "/app/inventario"
                },
                {
                    "nombre": "Entradas",
                    "descripcion": "En la pagina se muestra el historial de entradas",
                    "icon": "pi pi-directions-alt",
                    "childrens": [],
                    "tipo": "MENU",
                    "ruta": ""
                },
                {
                    "nombre": "Salidas",
                    "descripcion": "En la pagina se muestra el historial de Salidas",
                    "icon": "pi pi-directions",
                    "childrens": [],
                    "tipo": "MENU",
                    "ruta": ""
                }
            ],
            "tipo": "GRUPO_MENU",
            "ruta": ""
        },
        {
            "nombre": "ADMINISTRACION",
            "descripcion":"",
            "icon": "pi pi-warehouse",
            "childrens": [
                {
                    "nombre": "Categoria",
                    "descripcion": "En la pagina se muestra la lista de categorias",
                    "icon": "pi pi-palette",
                    "childrens": [],
                    "tipo": "MENU",
                    "ruta": ""
                },
                {
                    "nombre": "Clientes",
                    "descripcion": "En la pagina se muestran los clientes",
                    "icon": "pi pi-users",
                    "childrens": [],
                    "tipo": "MENU",
                    "ruta": ""
                },
                {
                    "nombre": "Color",
                    "descripcion": "En la pagina se muestra el listado de colores",
                    "icon": "pi pi-palette",
                    "childrens": [],
                    "tipo": "MENU",
                    "ruta": ""
                },
                {
                    "nombre": "Usuarios",
                    "descripcion": "En la pagina se muestra el listado de usuarios",
                    "icon": "pi pi-user",
                    "childrens": [],
                    "tipo": "MENU",
                    "ruta": ""
                }
            ],
            "tipo": "GRUPO_MENU",
            "ruta": ""
        }
    ]
}